tidyselect/__init__.py
tidyselect-0.0.1.dist-info/METADATA
tidyselect-0.0.1.dist-info/WHEEL
tidyselect-0.0.1.dist-info/top_level.txt
tidyselect-0.0.1.dist-info/RECORD
